HeadersToDict/HeadersToDict.py
HeadersToDict/__init__.py
HeadersToDict-1.0.6.dist-info/METADATA
HeadersToDict-1.0.6.dist-info/WHEEL
HeadersToDict-1.0.6.dist-info/top_level.txt
HeadersToDict-1.0.6.dist-info/RECORD
